{
  "db_name": "PostgreSQL",
  "query": "SELECT EXISTS(\n                    SELECT 1\n                    FROM mensajes\n                    WHERE conversacion_id = $1 AND id < $2\n                ) AS \"exists!\"",
  "describe": {
    "columns": [
      {
        "ordinal": 0,
        "name": "exists!",
        "type_info": "Bool"
      }
    ],
    "parameters": {
      "Left": [
        "Int4",
        "Int4"
      ]
    },
    "nullable": [
      null
    ]
  },
  "hash": "e16211ba58990e5220e269f60e0ae28fbcf049af3f48b08619b15b315c511cee"
}
