{
  "db_name": "PostgreSQL",
  "query": "\n            SELECT DISTINCT usuario_id AS \"usuario_id!\"\n            FROM reproducciones\n            WHERE created_at > NOW() - INTERVAL '24 hours'\n            LIMIT $1\n            ",
  "describe": {
    "columns": [
      {
        "ordinal": 0,
        "name": "usuario_id!",
        "type_info": "Int4"
      }
    ],
    "parameters": {
      "Left": [
        "Int8"
      ]
    },
    "nullable": [
      true
    ]
  },
  "hash": "9889fb768729f853a1e89c4fd8270e4649dc3f7fa20601824aba0cb0bbb0809d"
}
