{
  "db_name": "PostgreSQL",
  "query": "UPDATE relaciones_sample\n               SET verificada = $2,\n                   updated_at = NOW()\n               WHERE id = $1\n               RETURNING id AS \"id!\"",
  "describe": {
    "columns": [
      {
        "ordinal": 0,
        "name": "id!",
        "type_info": "Int4"
      }
    ],
    "parameters": {
      "Left": [
        "Int4",
        "Bool"
      ]
    },
    "nullable": [
      false
    ]
  },
  "hash": "efe062c18c165451043261db045dccc25b51f4b58c218faf845ee42763ce9cb0"
}
